{
  "telemetry.enableCrashReporter": false,
  "telemetry.enableTelemetry": false,
  "editor.tabSize": 2,
  "editor.renderWhitespace": "boundary",
  "editor.rulers": [
    100
  ],
  "editor.wordWrap": "on",
  "files.trimTrailingWhitespace": true,
  "files.insertFinalNewline": true,
  "files.trimFinalNewlines": true,
  "files.eol": "\n",
  "swaggerViewer.defaultPort": 10239,
  "swaggerViewer.previewInBrowser": true,
  "azureFunctions.showProjectWarning": false,
  "explorer.confirmDelete": false,
  "prettier.singleQuote": true,
  "typescript.referencesCodeLens.enabled": true,
  "[typescript]": {
    "editor.defaultFormatter": "esbenp.prettier-vscode"
  },
  "[typescriptreact]": {
    "editor.defaultFormatter": "esbenp.prettier-vscode"
  },
  "[python]": {
    "editor.tabSize": 4
  },
  "[rust]": {
    "editor.tabSize": 4
  },
  "[javascript]": {
    "editor.defaultFormatter": "esbenp.prettier-vscode"
  },
  "[javascriptreact]": {
    "editor.defaultFormatter": "esbenp.prettier-vscode"
  },
  "editor.fontFamily": "'Fira Code'",
  "editor.fontLigatures": "'ss01', 'ss02', 'ss03', 'ss04', 'ss05', 'ss06', 'zero', 'onum'"
}
